[{"id":"1","fecha":"2025-02-27","imagen":"test_image_1.png","likes":1,"resultados":[{"nombre":"ARMADYL","top":1},{"nombre":"7N","top":2},{"nombre":"T1","top":3},{"nombre":"ARENA","top":4},{"nombre":"ALQ MOB","top":5},{"nombre":"HELLSTAR","top":6},{"nombre":"21S","top":7},{"nombre":"AS PC","top":8}]},{"id":"2","fecha":"2025-02-27","imagen":"tabla_scrim_2.png","likes":0,"resultados":[{"nombre":"AS PC","top":1},{"nombre":"ARMADYL","top":2},{"nombre":"T1","top":3},{"nombre":"7N","top":4},{"nombre":"HELLSTAR","top":5},{"nombre":"21S","top":6},{"nombre":"ALQ MOB","top":7},{"nombre":"ARENA","top":8}]},{"id":"3","fecha":"2025-02-27","imagen":"tabla_scrim_3.png","likes":0,"resultados":[{"nombre":"AS PC","top":1},{"nombre":"ARMADYL","top":2},{"nombre":"T1","top":3},{"nombre":"7N","top":4},{"nombre":"HELLSTAR","top":5},{"nombre":"21S","top":6},{"nombre":"ALQ MOB","top":7},{"nombre":"ARENA","top":8}]},{"id":"4","fecha":"2025-02-27","imagen":"tabla_scrim_4.png","likes":0,"resultados":[{"nombre":"AS PC","top":1},{"nombre":"ARMADYL","top":2},{"nombre":"T1","top":3},{"nombre":"7N","top":4},{"nombre":"HELLSTAR","top":5},{"nombre":"21S","top":6},{"nombre":"ALQ MOB","top":7},{"nombre":"ARENA","top":8}]},{"id":"5","fecha":"2025-02-27","imagen":"tabla_scrim_5.png","likes":0,"resultados":[{"nombre":"AS PC","top":1},{"nombre":"ARMADYL","top":2},{"nombre":"T1","top":3},{"nombre":"7N","top":4},{"nombre":"HELLSTAR","top":5},{"nombre":"21S","top":6},{"nombre":"ALQ MOB","top":7},{"nombre":"ARENA","top":8}]},{"id":"6","fecha":"2025-02-27","imagen":"tabla_scrim_6.png","likes":0,"resultados":[{"nombre":"21S","top":1},{"nombre":"7N","top":2},{"nombre":"ALQ MOB","top":3},{"nombre":"T1","top":4},{"nombre":"ARMADYL","top":5},{"nombre":"HELLSTAR","top":6},{"nombre":"AS PC","top":7},{"nombre":"ARENA","top":8}]}]